[ 
  { 
    "appId" : undefined,
    "description" : undefined,
    "developer" : "Tinder Inc.",
    "developerId" : 725634363,
    "developerUrl" : "https://itunes.apple.com/au/developer/tinder-inc/id725634363?mt=8",
    "genreIds" : [ 
        "6012",
        "6005"
      ],
    "genres" : [ 
        "Lifestyle",
        "Social Networking"
      ],
    "icon" : "http://is5.mzstatic.com/image/thumb/Purple128/v4/12/cc/5a/12cc5a7c-903d-aac2-571d-451fdddd6ea5/AppIcon-1x_U007emarketing-85-220-0-4.png/200x200bb.png",
    "id" : "547702041",
    "released" : "2012-08-03",
    "title" : "Tinder",
    "url" : "https://itunes.apple.com/au/app/tinder/id547702041?mt=8"
  },
  { 
    "appId" : undefined,
    "description" : undefined,
    "developer" : "密境和风",
    "developerId" : 988396857,
    "developerUrl" : "https://itunes.apple.com/au/developer/%E5%AF%86%E5%A2%83%E5%92%8C%E9%A3%8E/id988396857?mt=8",
    "genreIds" : [ 
        "6005",
        "6008"
      ],
    "genres" : [ 
        "Social Networking",
        "Photo & Video"
      ],
    "icon" : "http://is4.mzstatic.com/image/thumb/Purple128/v4/71/af/8b/71af8b66-35a0-ee72-a6ed-cd849e2d9be1/AppIcon-1x_U007emarketing-85-220-3.png/200x200bb.png",
    "id" : "988396858",
    "released" : "2015-07-14",
    "title" : "花椒-3亿人都在玩的短直播视频交友社区",
    "url" : "https://itunes.apple.com/au/app/%E8%8A%B1%E6%A4%92-3%E4%BA%BF%E4%BA%BA%E9%83%BD%E5%9C%A8%E7%8E%A9%E7%9A%84%E7%9F%AD%E7%9B%B4%E6%92%AD%E8%A7%86%E9%A2%91%E4%BA%A4%E5%8F%8B%E7%A4%BE%E5%8C%BA/id988396858?mt=8"
  },
  { 
    "appId" : undefined,
    "description" : undefined,
    "developer" : "Product Madness",
    "developerId" : 525894639,
    "developerUrl" : "https://itunes.apple.com/au/developer/product-madness/id525894639?mt=8",
    "genreIds" : [ 
        "6014",
        "6016",
        "7006",
        "7005"
      ],
    "genres" : [ 
        "Games",
        "Entertainment",
        "Casino",
        "Card"
      ],
    "icon" : "http://is4.mzstatic.com/image/thumb/Purple128/v4/6c/6a/ea/6c6aea1c-db94-5d80-fbe5-6daf24e2fcc2/AppIcon-1x_U007emarketing-85-220-5.png/200x200bb.png",
    "id" : "785537179",
    "released" : "2014-07-26",
    "title" : "Heart of Vegas – Slots Casino",
    "url" : "https://itunes.apple.com/au/app/heart-of-vegas-slots-casino/id785537179?mt=8"
  },
  { 
    "appId" : undefined,
    "description" : undefined,
    "developer" : "Netflix, Inc.",
    "developerId" : 363590054,
    "developerUrl" : "https://itunes.apple.com/au/developer/netflix-inc/id363590054?mt=8",
    "genreIds" : [ 
        "6016",
        "6012"
      ],
    "genres" : [ 
        "Entertainment",
        "Lifestyle"
      ],
    "icon" : "http://is4.mzstatic.com/image/thumb/Purple118/v4/22/ff/ec/22ffec54-cb72-e575-af89-f6e37182d185/AppIcon-1x_U007emarketing-0-85-220-0-9.png/200x200bb.png",
    "id" : "363590051",
    "released" : "2015-03-20",
    "title" : "Netflix",
    "url" : "https://itunes.apple.com/au/app/netflix/id363590051?mt=8"
  },
  { 
    "appId" : undefined,
    "description" : undefined,
    "developer" : "Product Madness",
    "developerId" : 525894639,
    "developerUrl" : "https://itunes.apple.com/au/developer/product-madness/id525894639?mt=8",
    "genreIds" : [ 
        "6014",
        "7006",
        "6012"
      ],
    "genres" : [ 
        "Games",
        "Casino",
        "Lifestyle"
      ],
    "icon" : "http://is1.mzstatic.com/image/thumb/Purple118/v4/27/15/d0/2715d011-0187-200f-4a97-489511d6dc69/AppIcon-1x_U007emarketing-GLES2_U002c0-512MB-85-220-0-8.png/200x200bb.png",
    "id" : "1123582513",
    "released" : "2017-07-14",
    "title" : "Cashman Casino Vegas Slot Game",
    "url" : "https://itunes.apple.com/au/app/cashman-casino-vegas-slot-game/id1123582513?mt=8"
  },
  { 
    "appId" : undefined,
    "description" : undefined,
    "developer" : "Playtika LTD",
    "developerId" : 447553567,
    "developerUrl" : "https://itunes.apple.com/au/developer/playtika-ltd/id447553567?mt=8",
    "genreIds" : [ 
        "6014",
        "7006",
        "6016",
        "7005"
      ],
    "genres" : [ 
        "Games",
        "Casino",
        "Entertainment",
        "Card"
      ],
    "icon" : "http://is5.mzstatic.com/image/thumb/Purple118/v4/91/b1/de/91b1deeb-b0ef-d836-9acc-057fa5e74129/AppIcons-1x_U007emarketing-0-85-220-0-6.png/200x200bb.png",
    "id" : "447553564",
    "released" : "2011-11-07",
    "title" : "Slotomania Casino Online Slots",
    "url" : "https://itunes.apple.com/au/app/slotomania-casino-online-slots/id447553564?mt=8"
  },
  { 
    "appId" : undefined,
    "description" : undefined,
    "developer" : "Google, Inc.",
    "developerId" : 281956209,
    "developerUrl" : "https://itunes.apple.com/au/developer/google-inc/id281956209?mt=8",
    "genreIds" : [ 
        "6008",
        "6016"
      ],
    "genres" : [ 
        "Photo & Video",
        "Entertainment"
      ],
    "icon" : "http://is4.mzstatic.com/image/thumb/Purple128/v4/ff/aa/0f/ffaa0f1a-f3b1-ac16-8fc3-dfe8c5dd65ec/AppIcon-1x_U007emarketing-85-220-0-6.png/200x200bb.png",
    "id" : "544007664",
    "released" : "2012-09-11",
    "title" : "YouTube: Watch, Listen, Stream",
    "url" : "https://itunes.apple.com/au/app/youtube-watch-listen-stream/id544007664?mt=8"
  },
  { 
    "appId" : undefined,
    "description" : undefined,
    "developer" : "Niantic, Inc.",
    "developerId" : 1037205060,
    "developerUrl" : "https://itunes.apple.com/au/developer/niantic-inc/id1037205060?mt=8",
    "genreIds" : [ 
        "6014",
        "6013"
      ],
    "genres" : [ 
        "Games",
        "Health & Fitness"
      ],
    "icon" : "http://is2.mzstatic.com/image/thumb/Purple128/v4/de/4c/c4/de4cc428-30cb-5f59-1041-21f791666b86/AppIcon-1x_U007emarketing-85-220-0-8.png/200x200bb.png",
    "id" : "1094591345",
    "released" : "2016-07-05",
    "title" : "Pokémon GO",
    "url" : "https://itunes.apple.com/au/app/pok%C3%A9mon-go/id1094591345?mt=8"
  },
  { 
    "appId" : undefined,
    "description" : undefined,
    "developer" : "King",
    "developerId" : 526656015,
    "developerUrl" : "https://itunes.apple.com/au/developer/king/id526656015?mt=8",
    "genreIds" : [ 
        "6014",
        "6016",
        "7012",
        "7003"
      ],
    "genres" : [ 
        "Games",
        "Entertainment",
        "Puzzle",
        "Arcade"
      ],
    "icon" : "http://is2.mzstatic.com/image/thumb/Purple118/v4/e6/c3/59/e6c35971-e3a0-6cc2-9390-8fb3cd05f088/mzl.grceabah.png/200x200bb.png",
    "id" : "553834731",
    "released" : "2012-11-14",
    "title" : "Candy Crush Saga",
    "url" : "https://itunes.apple.com/au/app/candy-crush-saga/id553834731?mt=8"
  },
  { 
    "appId" : undefined,
    "description" : undefined,
    "developer" : "Supercell",
    "developerId" : 488106216,
    "developerUrl" : "https://itunes.apple.com/au/developer/supercell/id488106216?mt=8",
    "genreIds" : [ 
        "6014",
        "7001",
        "6016",
        "7017"
      ],
    "genres" : [ 
        "Games",
        "Action",
        "Entertainment",
        "Strategy"
      ],
    "icon" : "http://is4.mzstatic.com/image/thumb/Purple118/v4/1c/8d/63/1c8d634b-e034-f6ad-0e84-673d2b9c85b3/AppIcon-1x_U007emarketing-0-85-220-0-5.png/200x200bb.png",
    "id" : "529479190",
    "released" : "2012-08-02",
    "title" : "Clash of Clans",
    "url" : "https://itunes.apple.com/au/app/clash-of-clans/id529479190?mt=8"
  },
  { 
    "appId" : undefined,
    "description" : undefined,
    "developer" : "Zoosk, Inc.",
    "developerId" : 349160526,
    "developerUrl" : "https://itunes.apple.com/au/developer/zoosk-inc/id349160526?mt=8",
    "genreIds" : [ 
        "6005",
        "6012"
      ],
    "genres" : [ 
        "Social Networking",
        "Lifestyle"
      ],
    "icon" : "http://is4.mzstatic.com/image/thumb/Purple128/v4/7b/a3/21/7ba321bd-f23d-9f65-7f56-fe813aa5a8e1/AppIcon-1x_U007emarketing-85-220-9.png/200x200bb.png",
    "id" : "349160522",
    "released" : "2010-01-12",
    "title" : "Zoosk - #1 Dating App",
    "url" : "https://itunes.apple.com/au/app/zoosk-1-dating-app/id349160522?mt=8"
  },
  { 
    "appId" : undefined,
    "description" : undefined,
    "developer" : "Telstra Corporation Limited",
    "developerId" : 327529523,
    "developerUrl" : "https://itunes.apple.com/au/developer/telstra-corporation-limited/id327529523?mt=8",
    "genreIds" : [ 
        "6004",
        "6016"
      ],
    "genres" : [ 
        "Sports",
        "Entertainment"
      ],
    "icon" : "http://is5.mzstatic.com/image/thumb/Purple118/v4/8c/5b/aa/8c5baa0a-d683-8718-0358-ff2292417b5f/AppIcon-1x_U007emarketing-85-220-0-6.png/200x200bb.png",
    "id" : "415427158",
    "released" : "2011-03-27",
    "title" : "AFL Live Official App",
    "url" : "https://itunes.apple.com/au/app/afl-live-official-app/id415427158?mt=8"
  },
  { 
    "appId" : undefined,
    "description" : undefined,
    "developer" : "Pacific-Interactive ltd",
    "developerId" : 580824260,
    "developerUrl" : "https://itunes.apple.com/au/developer/pacific-interactive-ltd/id580824260?mt=8",
    "genreIds" : [ 
        "6014",
        "7006",
        "7005",
        "6016"
      ],
    "genres" : [ 
        "Games",
        "Casino",
        "Card",
        "Entertainment"
      ],
    "icon" : "http://is4.mzstatic.com/image/thumb/Purple128/v4/1e/6d/da/1e6dda99-27ab-879b-f7ab-1306288202b0/AppIcon-1x_U007emarketing-0-85-220-0-5.png/200x200bb.png",
    "id" : "586634331",
    "released" : "2013-01-09",
    "title" : "House of Fun Slots Casino",
    "url" : "https://itunes.apple.com/au/app/house-of-fun-slots-casino/id586634331?mt=8"
  },
  { 
    "appId" : undefined,
    "description" : undefined,
    "developer" : "Playrix Games",
    "developerId" : 1162116447,
    "developerUrl" : "https://itunes.apple.com/au/developer/playrix-games/id1162116447?mt=8",
    "genreIds" : [ 
        "6014",
        "7015",
        "6016",
        "7012"
      ],
    "genres" : [ 
        "Games",
        "Simulation",
        "Entertainment",
        "Puzzle"
      ],
    "icon" : "http://is1.mzstatic.com/image/thumb/Purple118/v4/6a/f2/75/6af27572-78d9-0bfc-e101-1dc4b8d1a3ce/AppIcon-1x_U007emarketing-0-85-220-0-9.png/200x200bb.png",
    "id" : "1105855019",
    "released" : "2016-06-07",
    "title" : "Gardenscapes",
    "url" : "https://itunes.apple.com/au/app/gardenscapes/id1105855019?mt=8"
  },
  { 
    "appId" : undefined,
    "description" : undefined,
    "developer" : "Playrix Games",
    "developerId" : 1162116447,
    "developerUrl" : "https://itunes.apple.com/au/developer/playrix-games/id1162116447?mt=8",
    "genreIds" : [ 
        "6014",
        "6016",
        "7012",
        "7015"
      ],
    "genres" : [ 
        "Games",
        "Entertainment",
        "Puzzle",
        "Simulation"
      ],
    "icon" : "http://is5.mzstatic.com/image/thumb/Purple118/v4/ca/bd/02/cabd026f-8efc-e121-d2bf-8562c1147369/AppIcon-1x_U007emarketing-85-220-9.png/200x200bb.png",
    "id" : "1195621598",
    "released" : "2017-08-23",
    "title" : "Homescapes",
    "url" : "https://itunes.apple.com/au/app/homescapes/id1195621598?mt=8"
  },
  { 
    "appId" : undefined,
    "description" : undefined,
    "developer" : "Telstra Corporation Limited",
    "developerId" : 327529523,
    "developerUrl" : "https://itunes.apple.com/au/developer/telstra-corporation-limited/id327529523?mt=8",
    "genreIds" : [ 
        "6004",
        "6016"
      ],
    "genres" : [ 
        "Sports",
        "Entertainment"
      ],
    "icon" : "http://is3.mzstatic.com/image/thumb/Purple118/v4/ef/ac/75/efac7570-f013-f643-59cb-8dd756b13c05/AppIcon-1x_U007emarketing-85-220-0-6.png/200x200bb.png",
    "id" : "442363523",
    "released" : "2011-07-06",
    "title" : "NRL Official App",
    "url" : "https://itunes.apple.com/au/app/nrl-official-app/id442363523?mt=8"
  },
  { 
    "appId" : undefined,
    "description" : undefined,
    "developer" : "Kabam",
    "developerId" : 445459903,
    "developerUrl" : "https://itunes.apple.com/au/developer/kabam/id445459903?mt=8",
    "genreIds" : [ 
        "6014",
        "7001",
        "7002",
        "6016"
      ],
    "genres" : [ 
        "Games",
        "Action",
        "Adventure",
        "Entertainment"
      ],
    "icon" : "http://is1.mzstatic.com/image/thumb/Purple118/v4/29/9e/b2/299eb229-a539-95fb-024d-73f50ad98005/AppIcon-1x_U007emarketing-0-85-220-0-5.png/200x200bb.png",
    "id" : "896112560",
    "released" : "2014-12-10",
    "title" : "MARVEL Contest of Champions",
    "url" : "https://itunes.apple.com/au/app/marvel-contest-of-champions/id896112560?mt=8"
  },
  { 
    "appId" : undefined,
    "description" : undefined,
    "developer" : "LinkedIn Corporation",
    "developerId" : 288429043,
    "developerUrl" : "https://itunes.apple.com/au/developer/linkedin-corporation/id288429043?mt=8",
    "genreIds" : [ 
        "6005",
        "6000"
      ],
    "genres" : [ 
        "Social Networking",
        "Business"
      ],
    "icon" : "http://is2.mzstatic.com/image/thumb/Purple62/v4/0f/ca/69/0fca69b7-bdd2-c5d7-0d88-d1e082eab604/AppIcon-1x_U007emarketing-85-220-0-5.png/200x200bb.png",
    "id" : "288429040",
    "released" : "2008-08-20",
    "title" : "LinkedIn",
    "url" : "https://itunes.apple.com/au/app/linkedin/id288429040?mt=8"
  },
  { 
    "appId" : undefined,
    "description" : undefined,
    "developer" : "Bumble Holding Limited",
    "developerId" : 1120675060,
    "developerUrl" : "https://itunes.apple.com/au/developer/bumble-holding-limited/id1120675060?mt=8",
    "genreIds" : [ 
        "6012",
        "6005"
      ],
    "genres" : [ 
        "Lifestyle",
        "Social Networking"
      ],
    "icon" : "http://is1.mzstatic.com/image/thumb/Purple128/v4/75/3f/ce/753fce7a-6c61-40e3-eb4d-b545a30ee120/AppIcon-1x_U007emarketing-0-0-GLES2_U002c0-512MB-sRGB-0-0-0-85-220-0-0-0-4.png/200x200bb.png",
    "id" : "930441707",
    "released" : "2014-12-03",
    "title" : "Bumble - Meet New People",
    "url" : "https://itunes.apple.com/au/app/bumble-meet-new-people/id930441707?mt=8"
  },
  { 
    "appId" : undefined,
    "description" : undefined,
    "developer" : "PlentyOfFish",
    "developerId" : 389638246,
    "developerUrl" : "https://itunes.apple.com/au/developer/plentyoffish/id389638246?mt=8",
    "genreIds" : [ 
        "6005",
        "6012"
      ],
    "genres" : [ 
        "Social Networking",
        "Lifestyle"
      ],
    "icon" : "http://is2.mzstatic.com/image/thumb/Purple118/v4/8f/3c/92/8f3c9294-fd06-d282-6ba1-171559798bcf/AppIcon-1x_U007emarketing-0-0-85-220-0-9.png/200x200bb.png",
    "id" : "389638243",
    "released" : "2010-09-17",
    "title" : "POF Dating",
    "url" : "https://itunes.apple.com/au/app/pof-dating/id389638243?mt=8"
  },
  { 
    "appId" : undefined,
    "description" : undefined,
    "developer" : "Pixelberry Studios",
    "developerId" : 575608309,
    "developerUrl" : "https://itunes.apple.com/au/developer/pixelberry-studios/id575608309?mt=8",
    "genreIds" : [ 
        "6014",
        "7014",
        "6016",
        "7015"
      ],
    "genres" : [ 
        "Games",
        "Role-Playing",
        "Entertainment",
        "Simulation"
      ],
    "icon" : "http://is3.mzstatic.com/image/thumb/Purple118/v4/8a/87/df/8a87df15-a915-16c5-e97b-76e0cb89a87f/AppIcon-1x_U007emarketing-85-220-6.png/200x200bb.png",
    "id" : "1071310449",
    "released" : "2016-08-20",
    "title" : "Choices: Stories You Play",
    "url" : "https://itunes.apple.com/au/app/choices-stories-you-play/id1071310449?mt=8"
  },
  { 
    "appId" : undefined,
    "description" : undefined,
    "developer" : "Zynga Inc.",
    "developerId" : 295913422,
    "developerUrl" : "https://itunes.apple.com/au/developer/zynga-inc/id295913422?mt=8",
    "genreIds" : [ 
        "6014",
        "6016",
        "7005",
        "7006"
      ],
    "genres" : [ 
        "Games",
        "Entertainment",
        "Card",
        "Casino"
      ],
    "icon" : "http://is4.mzstatic.com/image/thumb/Purple118/v4/f8/3c/e0/f83ce0cf-31bc-2aa0-a92e-a85c338ce185/mzl.ooauauel.jpg/200x200bb.png",
    "id" : "354902315",
    "released" : "2010-05-14",
    "title" : "Zynga Poker - Texas Holdem",
    "url" : "https://itunes.apple.com/au/app/zynga-poker-texas-holdem/id354902315?mt=8"
  },
  { 
    "appId" : undefined,
    "description" : undefined,
    "developer" : "The Bikini Body Training Company Pty Ltd",
    "developerId" : 1049234586,
    "developerUrl" : "https://itunes.apple.com/au/developer/the-bikini-body-training-company-pty-ltd/id1049234586?mt=8",
    "genreIds" : [ 
        "6013",
        "6012"
      ],
    "genres" : [ 
        "Health & Fitness",
        "Lifestyle"
      ],
    "icon" : "http://is5.mzstatic.com/image/thumb/Purple62/v4/e2/bc/c2/e2bcc28c-986d-70c0-ec00-4f779d62f9cb/AppIcon-1x_U007emarketing-85-220-0-9.png/200x200bb.png",
    "id" : "1049234587",
    "released" : "2015-11-19",
    "title" : "Sweat: Kayla Itsines Fitness",
    "url" : "https://itunes.apple.com/au/app/sweat-kayla-itsines-fitness/id1049234587?mt=8"
  },
  { 
    "appId" : undefined,
    "description" : undefined,
    "developer" : "Spotify Ltd.",
    "developerId" : 324684583,
    "developerUrl" : "https://itunes.apple.com/au/developer/spotify-ltd/id324684583?mt=8",
    "genreIds" : [ 
        "6011",
        "6016"
      ],
    "genres" : [ 
        "Music",
        "Entertainment"
      ],
    "icon" : "http://is3.mzstatic.com/image/thumb/Purple128/v4/c4/45/dd/c445ddcb-11cc-fae5-d6a9-1e9d16e1860b/AppIcon-1x_U007emarketing-85-220-0-5.png/200x200bb.png",
    "id" : "324684580",
    "released" : "2012-05-21",
    "title" : "Spotify Music",
    "url" : "https://itunes.apple.com/au/app/spotify-music/id324684580?mt=8"
  },
  { 
    "appId" : undefined,
    "description" : undefined,
    "developer" : "King",
    "developerId" : 526656015,
    "developerUrl" : "https://itunes.apple.com/au/developer/king/id526656015?mt=8",
    "genreIds" : [ 
        "6014",
        "7003",
        "7012"
      ],
    "genres" : [ 
        "Games",
        "Arcade",
        "Puzzle"
      ],
    "icon" : "http://is2.mzstatic.com/image/thumb/Purple128/v4/ec/a6/1c/eca61c07-3626-4d04-f579-3efa794666c9/pr_source.png/200x200bb.png",
    "id" : "850417475",
    "released" : "2014-11-11",
    "title" : "Candy Crush Soda Saga",
    "url" : "https://itunes.apple.com/au/app/candy-crush-soda-saga/id850417475?mt=8"
  },
  { 
    "appId" : undefined,
    "description" : undefined,
    "developer" : "Supercell",
    "developerId" : 488106216,
    "developerUrl" : "https://itunes.apple.com/au/developer/supercell/id488106216?mt=8",
    "genreIds" : [ 
        "6014",
        "7017",
        "6016",
        "7001"
      ],
    "genres" : [ 
        "Games",
        "Strategy",
        "Entertainment",
        "Action"
      ],
    "icon" : "http://is4.mzstatic.com/image/thumb/Purple118/v4/58/28/9e/58289ecc-f6e3-e79b-a183-258f5aedbedf/AppIcon-1x_U007emarketing-0-85-220-0-5.png/200x200bb.png",
    "id" : "1053012308",
    "released" : "2016-01-04",
    "title" : "Clash Royale",
    "url" : "https://itunes.apple.com/au/app/clash-royale/id1053012308?mt=8"
  },
  { 
    "appId" : undefined,
    "description" : undefined,
    "developer" : "Peak Games",
    "developerId" : 476160947,
    "developerUrl" : "https://itunes.apple.com/au/developer/peak-games/id476160947?mt=8",
    "genreIds" : [ 
        "6014",
        "7003",
        "7012"
      ],
    "genres" : [ 
        "Games",
        "Arcade",
        "Puzzle"
      ],
    "icon" : "http://is4.mzstatic.com/image/thumb/Purple128/v4/b8/bf/28/b8bf28af-5f9a-03f7-d4db-a5ea2b0c5e0a/AppIcon-1x_U007emarketing-0-85-220-0-8.png/200x200bb.png",
    "id" : "1176027022",
    "released" : "2017-08-15",
    "title" : "Toon Blast",
    "url" : "https://itunes.apple.com/au/app/toon-blast/id1176027022?mt=8"
  },
  { 
    "appId" : undefined,
    "description" : undefined,
    "developer" : "Electronic Arts",
    "developerId" : 284800461,
    "developerUrl" : "https://itunes.apple.com/au/developer/electronic-arts/id284800461?mt=8",
    "genreIds" : [ 
        "6014",
        "7017",
        "7014"
      ],
    "genres" : [ 
        "Games",
        "Strategy",
        "Role-Playing"
      ],
    "icon" : "http://is3.mzstatic.com/image/thumb/Purple128/v4/6d/ed/36/6ded360f-70ae-0f69-cbe5-7a89aa65076e/AppIcon-1x_U007emarketing-85-220-8.png/200x200bb.png",
    "id" : "921022358",
    "released" : "2015-09-29",
    "title" : "Star Wars™: Galaxy of Heroes",
    "url" : "https://itunes.apple.com/au/app/star-wars-galaxy-of-heroes/id921022358?mt=8"
  },
  { 
    "appId" : undefined,
    "description" : undefined,
    "developer" : "Calm.com",
    "developerId" : 571800813,
    "developerUrl" : "https://itunes.apple.com/au/developer/calm-com/id571800813?mt=8",
    "genreIds" : [ 
        "6013",
        "6012"
      ],
    "genres" : [ 
        "Health & Fitness",
        "Lifestyle"
      ],
    "icon" : "http://is3.mzstatic.com/image/thumb/Purple118/v4/dd/ec/10/ddec10cc-d7bf-ecf0-a3ea-272e8a707b93/AppIcon-1x_U007emarketing-85-220-0-9.png/200x200bb.png",
    "id" : "571800810",
    "released" : "2013-02-22",
    "title" : "Calm",
    "url" : "https://itunes.apple.com/au/app/calm/id571800810?mt=8"
  },
  { 
    "appId" : undefined,
    "description" : undefined,
    "developer" : "Warner Bros.",
    "developerId" : 298372283,
    "developerUrl" : "https://itunes.apple.com/au/developer/warner-bros/id298372283?mt=8",
    "genreIds" : [ 
        "6014",
        "7017",
        "7001"
      ],
    "genres" : [ 
        "Games",
        "Strategy",
        "Action"
      ],
    "icon" : "http://is2.mzstatic.com/image/thumb/Purple118/v4/66/14/e4/6614e4ea-fa3a-5739-dc1a-e0683b89524e/AppIcon-1x_U007emarketing-0-0-GLES2_U002c0-512MB-sRGB-0-0-0-85-220-0-0-0-7.png/200x200bb.png",
    "id" : "1035712810",
    "released" : "2017-08-02",
    "title" : "Game of Thrones: Conquest™",
    "url" : "https://itunes.apple.com/au/app/game-of-thrones-conquest/id1035712810?mt=8"
  },
  { 
    "appId" : undefined,
    "description" : undefined,
    "developer" : "IGG.COM",
    "developerId" : 1303288190,
    "developerUrl" : "https://itunes.apple.com/au/developer/igg-com/id1303288190?mt=8",
    "genreIds" : [ 
        "6014",
        "7017",
        "7014"
      ],
    "genres" : [ 
        "Games",
        "Strategy",
        "Role-Playing"
      ],
    "icon" : "http://is4.mzstatic.com/image/thumb/Purple128/v4/c5/64/c5/c564c51f-1217-96d9-0905-f754bd919d43/AppIcon-1x_U007emarketing-0-85-220-0-5.png/200x200bb.png",
    "id" : "1071976327",
    "released" : "2016-03-31",
    "title" : "Lords Mobile",
    "url" : "https://itunes.apple.com/au/app/lords-mobile/id1071976327?mt=8"
  },
  { 
    "appId" : undefined,
    "description" : undefined,
    "developer" : "Epic Action LLC",
    "developerId" : 1140629705,
    "developerUrl" : "https://itunes.apple.com/au/developer/epic-action-llc/id1140629705?mt=8",
    "genreIds" : [ 
        "6014",
        "7017",
        "7014",
        "6005"
      ],
    "genres" : [ 
        "Games",
        "Strategy",
        "Role-Playing",
        "Social Networking"
      ],
    "icon" : "http://is2.mzstatic.com/image/thumb/Purple128/v4/c5/55/7c/c5557cf1-1ff7-66d0-0bdf-aec6ff0736c0/mzl.uxogjpiq.jpg/200x200bb.png",
    "id" : "1186994231",
    "released" : "2017-03-31",
    "title" : "Final Fantasy XV: A New Empire",
    "url" : "https://itunes.apple.com/au/app/final-fantasy-xv-a-new-empire/id1186994231?mt=8"
  },
  { 
    "appId" : undefined,
    "description" : undefined,
    "developer" : "FunPlus",
    "developerId" : 495598783,
    "developerUrl" : "https://itunes.apple.com/au/developer/funplus/id495598783?mt=8",
    "genreIds" : [ 
        "6014",
        "7017",
        "7014"
      ],
    "genres" : [ 
        "Games",
        "Strategy",
        "Role-Playing"
      ],
    "icon" : "http://is1.mzstatic.com/image/thumb/Purple118/v4/9c/ce/13/9cce13ca-9fc9-fe24-b095-053bd74b708e/mzl.ctethjtg.png/200x200bb.png",
    "id" : "1274354704",
    "released" : "2017-09-21",
    "title" : "Guns of Glory",
    "url" : "https://itunes.apple.com/au/app/guns-of-glory/id1274354704?mt=8"
  },
  { 
    "appId" : undefined,
    "description" : undefined,
    "developer" : "Google, Inc.",
    "developerId" : 281956209,
    "developerUrl" : "https://itunes.apple.com/au/developer/google-inc/id281956209?mt=8",
    "genreIds" : [ 
        "6011",
        "6016"
      ],
    "genres" : [ 
        "Music",
        "Entertainment"
      ],
    "icon" : "http://is2.mzstatic.com/image/thumb/Purple128/v4/19/ff/a3/19ffa389-7a65-1fad-2ce4-5135530f2027/AppIcon-1x_U007emarketing-85-220-0-5.png/200x200bb.png",
    "id" : "1017492454",
    "released" : "2016-05-17",
    "title" : "YouTube Music",
    "url" : "https://itunes.apple.com/au/app/youtube-music/id1017492454?mt=8"
  },
  { 
    "appId" : undefined,
    "description" : undefined,
    "developer" : "DGN Games, LLC",
    "developerId" : 919141987,
    "developerUrl" : "https://itunes.apple.com/au/developer/dgn-games-llc/id919141987?mt=8",
    "genreIds" : [ 
        "6014",
        "7006",
        "6016"
      ],
    "genres" : [ 
        "Games",
        "Casino",
        "Entertainment"
      ],
    "icon" : "http://is5.mzstatic.com/image/thumb/Purple118/v4/62/7d/27/627d27a2-036c-260f-fc92-0382c05c0819/mzl.nkbqvcms.png/200x200bb.png",
    "id" : "1056662247",
    "released" : "2016-02-10",
    "title" : "Lucky Time Slots Casino Pokies",
    "url" : "https://itunes.apple.com/au/app/lucky-time-slots-casino-pokies/id1056662247?mt=8"
  },
  { 
    "appId" : undefined,
    "description" : undefined,
    "developer" : "Com2uS Corp.",
    "developerId" : 299175870,
    "developerUrl" : "https://itunes.apple.com/au/developer/com2us-corp/id299175870?mt=8",
    "genreIds" : [ 
        "6014",
        "7014",
        "6016",
        "7017"
      ],
    "genres" : [ 
        "Games",
        "Role-Playing",
        "Entertainment",
        "Strategy"
      ],
    "icon" : "http://is1.mzstatic.com/image/thumb/Purple128/v4/fb/c7/15/fbc7154f-5d43-0d1e-daa5-05fbadba1c7c/AppIcon-1x_U007emarketing-85-220-9.png/200x200bb.png",
    "id" : "852912420",
    "released" : "2014-06-12",
    "title" : "Summoners War",
    "url" : "https://itunes.apple.com/au/app/summoners-war/id852912420?mt=8"
  },
  { 
    "appId" : undefined,
    "description" : undefined,
    "developer" : "Smule",
    "developerId" : 290596339,
    "developerUrl" : "https://itunes.apple.com/au/developer/smule/id290596339?mt=8",
    "genreIds" : [ 
        "6011",
        "6016"
      ],
    "genres" : [ 
        "Music",
        "Entertainment"
      ],
    "icon" : "http://is5.mzstatic.com/image/thumb/Purple128/v4/e2/8b/7a/e28b7a0f-62ed-e7a6-7ac7-6d2b6f03c661/AppIcon-CCCP-1x_U007emarketing-85-220-0-9.png/200x200bb.png",
    "id" : "509993510",
    "released" : "2012-08-08",
    "title" : "Sing! by Smule",
    "url" : "https://itunes.apple.com/au/app/sing-by-smule/id509993510?mt=8"
  },
  { 
    "appId" : undefined,
    "description" : undefined,
    "developer" : "SoundCloud Ltd.",
    "developerId" : 336353154,
    "developerUrl" : "https://itunes.apple.com/au/developer/soundcloud-ltd/id336353154?mt=8",
    "genreIds" : [ 
        "6011",
        "6005"
      ],
    "genres" : [ 
        "Music",
        "Social Networking"
      ],
    "icon" : "http://is5.mzstatic.com/image/thumb/Purple118/v4/b0/26/1a/b0261afa-10c9-c822-a8c3-110399c6eaa5/AppIcon-1x_U007emarketing-85-220-0-6.png/200x200bb.png",
    "id" : "336353151",
    "released" : "2009-11-03",
    "title" : "SoundCloud - Music & Audio",
    "url" : "https://itunes.apple.com/au/app/soundcloud-music-audio/id336353151?mt=8"
  },
  { 
    "appId" : undefined,
    "description" : undefined,
    "developer" : "Peak Games",
    "developerId" : 476160947,
    "developerUrl" : "https://itunes.apple.com/au/developer/peak-games/id476160947?mt=8",
    "genreIds" : [ 
        "6014",
        "7003",
        "7012"
      ],
    "genres" : [ 
        "Games",
        "Arcade",
        "Puzzle"
      ],
    "icon" : "http://is3.mzstatic.com/image/thumb/Purple118/v4/76/13/22/7613225f-be55-1e03-d88e-9fc135dc8509/AppIcon-1x_U007emarketing-0-85-220-0-5.png/200x200bb.png",
    "id" : "890378044",
    "released" : "2015-01-06",
    "title" : "Toy Blast",
    "url" : "https://itunes.apple.com/au/app/toy-blast/id890378044?mt=8"
  },
  { 
    "appId" : undefined,
    "description" : undefined,
    "developer" : "QIYI",
    "developerId" : 387327025,
    "developerUrl" : "https://itunes.apple.com/au/developer/qiyi/id387327025?mt=8",
    "genreIds" : [ 
        "6016",
        "6002"
      ],
    "genres" : [ 
        "Entertainment",
        "Utilities"
      ],
    "icon" : "http://is1.mzstatic.com/image/thumb/Purple118/v4/4c/d6/d8/4cd6d820-9d59-a58d-facc-fe63cd4c0b5d/IPhone_AppIcon-1x_U007emarketing-85-220-3.png/200x200bb.png",
    "id" : "393765873",
    "released" : "2010-09-26",
    "title" : "爱奇艺",
    "url" : "https://itunes.apple.com/au/app/%E7%88%B1%E5%A5%87%E8%89%BA/id393765873?mt=8"
  },
  { 
    "appId" : undefined,
    "description" : undefined,
    "developer" : "Dropbox",
    "developerId" : 327630333,
    "developerUrl" : "https://itunes.apple.com/au/developer/dropbox/id327630333?mt=8",
    "genreIds" : [ 
        "6007",
        "6002"
      ],
    "genres" : [ 
        "Productivity",
        "Utilities"
      ],
    "icon" : "http://is4.mzstatic.com/image/thumb/Purple128/v4/72/9b/1f/729b1f47-8b47-0cf9-0a62-4b8c3e45d7e6/AppIcon-1x_U007emarketing-85-220-0-5.png/200x200bb.png",
    "id" : "327630330",
    "released" : "2009-09-29",
    "title" : "Dropbox",
    "url" : "https://itunes.apple.com/au/app/dropbox/id327630330?mt=8"
  },
  { 
    "appId" : undefined,
    "description" : undefined,
    "developer" : "Nintendo Co., Ltd.",
    "developerId" : 1062496488,
    "developerUrl" : "https://itunes.apple.com/au/developer/nintendo-co-ltd/id1062496488?mt=8",
    "genreIds" : [ 
        "6014",
        "7017",
        "7014"
      ],
    "genres" : [ 
        "Games",
        "Strategy",
        "Role-Playing"
      ],
    "icon" : "http://is3.mzstatic.com/image/thumb/Purple62/v4/e2/cd/33/e2cd3348-7e72-2585-d67e-f133b9d716ab/AppIcon-1x_U007emarketing-85-220-5.png/200x200bb.png",
    "id" : "1181774280",
    "released" : "2017-02-02",
    "title" : "Fire Emblem Heroes",
    "url" : "https://itunes.apple.com/au/app/fire-emblem-heroes/id1181774280?mt=8"
  },
  { 
    "appId" : undefined,
    "description" : undefined,
    "developer" : "Crowdstar Inc",
    "developerId" : 321598392,
    "developerUrl" : "https://itunes.apple.com/au/developer/crowdstar-inc/id321598392?mt=8",
    "genreIds" : [ 
        "6014",
        "7015",
        "6012"
      ],
    "genres" : [ 
        "Games",
        "Simulation",
        "Lifestyle"
      ],
    "icon" : "http://is1.mzstatic.com/image/thumb/Purple118/v4/ae/1d/74/ae1d7451-4109-ee91-6cf0-a3498d862491/AppIcon-1x_U007emarketing-0-85-220-0-8.png/200x200bb.png",
    "id" : "1010962391",
    "released" : "2016-10-06",
    "title" : "Design Home",
    "url" : "https://itunes.apple.com/au/app/design-home/id1010962391?mt=8"
  },
  { 
    "appId" : undefined,
    "description" : undefined,
    "developer" : "droidhang",
    "developerId" : 463987809,
    "developerUrl" : "https://itunes.apple.com/au/developer/droidhang/id463987809?mt=8",
    "genreIds" : [ 
        "6014",
        "7017",
        "7014"
      ],
    "genres" : [ 
        "Games",
        "Strategy",
        "Role-Playing"
      ],
    "icon" : "http://is2.mzstatic.com/image/thumb/Purple118/v4/a8/4d/bf/a84dbf1d-678d-a1ba-41f6-433c2a2bed14/AppIcon-1x_U007emarketing-0-85-220-0-9.png/200x200bb.png",
    "id" : "1153461915",
    "released" : "2016-11-09",
    "title" : "Idle Heroes - Idle Games",
    "url" : "https://itunes.apple.com/au/app/idle-heroes-idle-games/id1153461915?mt=8"
  },
  { 
    "appId" : undefined,
    "description" : undefined,
    "developer" : "moonton",
    "developerId" : 910435102,
    "developerUrl" : "https://itunes.apple.com/au/developer/moonton/id910435102?mt=8",
    "genreIds" : [ 
        "6014",
        "7001",
        "7017",
        "6016"
      ],
    "genres" : [ 
        "Games",
        "Action",
        "Strategy",
        "Entertainment"
      ],
    "icon" : "http://is1.mzstatic.com/image/thumb/Purple128/v4/bc/4d/47/bc4d470e-3d65-6aba-9e9e-fcfbe6cfdf44/AppIcon-1x_U007emarketing-0-85-220-0-4.png/200x200bb.png",
    "id" : "1160056295",
    "released" : "2016-11-12",
    "title" : "Mobile Legends: Bang Bang",
    "url" : "https://itunes.apple.com/au/app/mobile-legends-bang-bang/id1160056295?mt=8"
  },
  { 
    "appId" : undefined,
    "description" : undefined,
    "developer" : "ELEX Wireless",
    "developerId" : 424770549,
    "developerUrl" : "https://itunes.apple.com/au/developer/elex-wireless/id424770549?mt=8",
    "genreIds" : [ 
        "6014",
        "7014",
        "7009",
        "6005"
      ],
    "genres" : [ 
        "Games",
        "Role-Playing",
        "Family",
        "Social Networking"
      ],
    "icon" : "http://is3.mzstatic.com/image/thumb/Purple118/v4/f0/9b/4f/f09b4f4c-c3c2-2457-a3a8-87346c195f06/mzl.ytlvabsv.png/200x200bb.png",
    "id" : "1214763767",
    "released" : "2017-05-05",
    "title" : "Love Nikki-Dress UP Queen",
    "url" : "https://itunes.apple.com/au/app/love-nikki-dress-up-queen/id1214763767?mt=8"
  },
  { 
    "appId" : undefined,
    "description" : undefined,
    "developer" : "MyFitnessPal.com",
    "developerId" : 341232721,
    "developerUrl" : "https://itunes.apple.com/au/developer/myfitnesspal-com/id341232721?mt=8",
    "genreIds" : [ 
        "6013",
        "6012"
      ],
    "genres" : [ 
        "Health & Fitness",
        "Lifestyle"
      ],
    "icon" : "http://is2.mzstatic.com/image/thumb/Purple128/v4/79/6a/59/796a59d3-ebad-e8a0-8472-b50c689d3c09/AppIcon-1x_U007emarketing-0-0-GLES2_U002c0-512MB-sRGB-0-0-0-85-220-0-0-0-6.png/200x200bb.png",
    "id" : "341232718",
    "released" : "2009-12-08",
    "title" : "MyFitnessPal",
    "url" : "https://itunes.apple.com/au/app/myfitnesspal/id341232718?mt=8"
  },
  { 
    "appId" : undefined,
    "description" : undefined,
    "developer" : "Headspace meditation limited",
    "developerId" : 384434796,
    "developerUrl" : "https://itunes.apple.com/au/developer/headspace-meditation-limited/id384434796?mt=8",
    "genreIds" : [ 
        "6013",
        "6007"
      ],
    "genres" : [ 
        "Health & Fitness",
        "Productivity"
      ],
    "icon" : "http://is1.mzstatic.com/image/thumb/Purple118/v4/52/92/54/5292549a-fd66-f20e-0f6f-fe75835b8252/AppIcon-1x_U007emarketing-85-220-0-6.png/200x200bb.png",
    "id" : "493145008",
    "released" : "2012-02-02",
    "title" : "Headspace: Guided Meditation",
    "url" : "https://itunes.apple.com/au/app/headspace-guided-meditation/id493145008?mt=8"
  },
  { 
    "appId" : undefined,
    "description" : undefined,
    "developer" : "Grindr LLC",
    "developerId" : 308956626,
    "developerUrl" : "https://itunes.apple.com/au/developer/grindr-llc/id308956626?mt=8",
    "genreIds" : [ 
        "6005",
        "6012"
      ],
    "genres" : [ 
        "Social Networking",
        "Lifestyle"
      ],
    "icon" : "http://is4.mzstatic.com/image/thumb/Purple128/v4/f7/fd/a4/f7fda4f0-8b09-c6ad-9aff-93fa6054dd40/AppIcon-1x_U007emarketing-85-220-8.png/200x200bb.png",
    "id" : "319881193",
    "released" : "2009-06-25",
    "title" : "Grindr - Gay chat",
    "url" : "https://itunes.apple.com/au/app/grindr-gay-chat/id319881193?mt=8"
  },
  { 
    "appId" : undefined,
    "description" : undefined,
    "developer" : "Episode Interactive",
    "developerId" : 761807761,
    "developerUrl" : "https://itunes.apple.com/au/developer/episode-interactive/id761807761?mt=8",
    "genreIds" : [ 
        "6014",
        "7014",
        "7015",
        "6016"
      ],
    "genres" : [ 
        "Games",
        "Role-Playing",
        "Simulation",
        "Entertainment"
      ],
    "icon" : "http://is5.mzstatic.com/image/thumb/Purple118/v4/79/ac/ad/79acadd8-b883-c709-ca10-fe77305ff036/AppIcon-1x_U007emarketing-85-220-9.png/200x200bb.png",
    "id" : "656971078",
    "released" : "2013-12-18",
    "title" : "Episode - Choose Your Story",
    "url" : "https://itunes.apple.com/au/app/episode-choose-your-story/id656971078?mt=8"
  },
  { 
    "appId" : undefined,
    "description" : undefined,
    "developer" : "Pocket Gems, Inc.",
    "developerId" : 335932431,
    "developerUrl" : "https://itunes.apple.com/au/developer/pocket-gems-inc/id335932431?mt=8",
    "genreIds" : [ 
        "6014",
        "6016",
        "7017",
        "7001"
      ],
    "genres" : [ 
        "Games",
        "Entertainment",
        "Strategy",
        "Action"
      ],
    "icon" : "http://is3.mzstatic.com/image/thumb/Purple128/v4/71/29/8d/71298dd7-0931-b479-ab88-872f9d35fc68/AppIcon-1x_U007emarketing-85-220-6.png/200x200bb.png",
    "id" : "958763157",
    "released" : "2015-04-16",
    "title" : "War Dragons",
    "url" : "https://itunes.apple.com/au/app/war-dragons/id958763157?mt=8"
  },
  { 
    "appId" : undefined,
    "description" : undefined,
    "developer" : "DoubleUGames Co., Ltd.",
    "developerId" : 642727746,
    "developerUrl" : "https://itunes.apple.com/au/developer/doubleugames-co-ltd/id642727746?mt=8",
    "genreIds" : [ 
        "6014",
        "7006",
        "7005"
      ],
    "genres" : [ 
        "Games",
        "Casino",
        "Card"
      ],
    "icon" : "http://is1.mzstatic.com/image/thumb/Purple128/v4/e3/31/9a/e3319a32-9b0d-490a-a911-6d354efb89b0/AppIcon-1x_U007emarketing-0-85-220-0-8.png/200x200bb.png",
    "id" : "642727743",
    "released" : "2013-09-23",
    "title" : "DoubleU Casino: Vegas Slots",
    "url" : "https://itunes.apple.com/au/app/doubleu-casino-vegas-slots/id642727743?mt=8"
  },
  { 
    "appId" : undefined,
    "description" : undefined,
    "developer" : "Miniclip.com",
    "developerId" : 337457683,
    "developerUrl" : "https://itunes.apple.com/au/developer/miniclip-com/id337457683?mt=8",
    "genreIds" : [ 
        "6014",
        "6016",
        "7016",
        "7015"
      ],
    "genres" : [ 
        "Games",
        "Entertainment",
        "Sports",
        "Simulation"
      ],
    "icon" : "http://is2.mzstatic.com/image/thumb/Purple118/v4/e1/3c/4c/e13c4cc0-cfe1-7509-9b5b-140ab46fdb08/mzl.zumjjfib.png/200x200bb.png",
    "id" : "543186831",
    "released" : "2013-02-27",
    "title" : "8 Ball Pool™",
    "url" : "https://itunes.apple.com/au/app/8-ball-pool/id543186831?mt=8"
  },
  { 
    "appId" : undefined,
    "description" : undefined,
    "developer" : "Playtika LTD",
    "developerId" : 447553567,
    "developerUrl" : "https://itunes.apple.com/au/developer/playtika-ltd/id447553567?mt=8",
    "genreIds" : [ 
        "6014",
        "6016",
        "7005",
        "7006"
      ],
    "genres" : [ 
        "Games",
        "Entertainment",
        "Card",
        "Casino"
      ],
    "icon" : "http://is3.mzstatic.com/image/thumb/Purple128/v4/b4/a6/96/b4a69699-7f1d-81e9-da54-041cc70fcce6/mzl.skpxrskm.jpg/200x200bb.png",
    "id" : "719525810",
    "released" : "2013-11-20",
    "title" : "World Series of Poker - WSOP",
    "url" : "https://itunes.apple.com/au/app/world-series-of-poker-wsop/id719525810?mt=8"
  },
  { 
    "appId" : undefined,
    "description" : undefined,
    "developer" : "Glu Games Inc",
    "developerId" : 284419051,
    "developerUrl" : "https://itunes.apple.com/au/developer/glu-games-inc/id284419051?mt=8",
    "genreIds" : [ 
        "6014",
        "6016",
        "7002",
        "7014"
      ],
    "genres" : [ 
        "Games",
        "Entertainment",
        "Adventure",
        "Role-Playing"
      ],
    "icon" : "http://is5.mzstatic.com/image/thumb/Purple128/v4/c4/30/d1/c430d162-848c-418e-eb5e-5249ea1ab32a/mzl.jueypckw.png/200x200bb.png",
    "id" : "860822992",
    "released" : "2014-06-24",
    "title" : "Kim Kardashian: Hollywood",
    "url" : "https://itunes.apple.com/au/app/kim-kardashian-hollywood/id860822992?mt=8"
  },
  { 
    "appId" : undefined,
    "description" : undefined,
    "developer" : "BIGO TECHNOLOGY PTE. LTD.",
    "developerId" : 940017134,
    "developerUrl" : "https://itunes.apple.com/au/developer/bigo-technology-pte-ltd/id940017134?mt=8",
    "genreIds" : [ 
        "6005",
        "6016"
      ],
    "genres" : [ 
        "Social Networking",
        "Entertainment"
      ],
    "icon" : "http://is5.mzstatic.com/image/thumb/Purple128/v4/a4/5f/9e/a45f9e4f-b135-c119-ca15-127387ec71f4/AppIcon-1x_U007emarketing-0-85-220-0-9.png/200x200bb.png",
    "id" : "1077137248",
    "released" : "2016-03-12",
    "title" : "BIGO LIVE - Live Stream",
    "url" : "https://itunes.apple.com/au/app/bigo-live-live-stream/id1077137248?mt=8"
  },
  { 
    "appId" : undefined,
    "description" : undefined,
    "developer" : "Xia Zhang",
    "developerId" : 1342134534,
    "developerUrl" : "https://itunes.apple.com/au/developer/xia-zhang/id1342134534?mt=8",
    "genreIds" : [ "6016" ],
    "genres" : [ "Entertainment" ],
    "icon" : "http://is2.mzstatic.com/image/thumb/Purple118/v4/1e/46/e5/1e46e57a-289c-7bbc-d20f-15421e18455c/AppIcon-1x_U007emarketing-85-220-4.png/200x200bb.png",
    "id" : "1342134535",
    "released" : "2018-02-02",
    "title" : "Emoji+ —Creative Emojis",
    "url" : "https://itunes.apple.com/au/app/emoji-creative-emojis/id1342134535?mt=8"
  },
  { 
    "appId" : undefined,
    "description" : undefined,
    "developer" : "Skype Communications S.a.r.l",
    "developerId" : 304219585,
    "developerUrl" : "https://itunes.apple.com/au/developer/skype-communications-s-a-r-l/id304219585?mt=8",
    "genreIds" : [ 
        "6005",
        "6007"
      ],
    "genres" : [ 
        "Social Networking",
        "Productivity"
      ],
    "icon" : "http://is5.mzstatic.com/image/thumb/Purple128/v4/b8/cd/e4/b8cde41e-dd9e-d10f-e5a0-4214f7ed4eeb/AppIcon-1x_U007emarketing-85-220-0-3.png/200x200bb.png",
    "id" : "304878510",
    "released" : "2009-03-31",
    "title" : "Skype for iPhone",
    "url" : "https://itunes.apple.com/au/app/skype-for-iphone/id304878510?mt=8"
  },
  { 
    "appId" : undefined,
    "description" : undefined,
    "developer" : "Big Fish Games, Inc",
    "developerId" : 292594310,
    "developerUrl" : "https://itunes.apple.com/au/developer/big-fish-games-inc/id292594310?mt=8",
    "genreIds" : [ 
        "6014",
        "6016",
        "7006",
        "7005"
      ],
    "genres" : [ 
        "Games",
        "Entertainment",
        "Casino",
        "Card"
      ],
    "icon" : "http://is2.mzstatic.com/image/thumb/Purple128/v4/3d/a1/1a/3da11ae7-2786-c0d9-0c60-c19770fa4af5/mzl.ocdpljiq.jpg/200x200bb.png",
    "id" : "538212549",
    "released" : "2012-08-16",
    "title" : "Big Fish Casino: Online Pokies",
    "url" : "https://itunes.apple.com/au/app/big-fish-casino-online-pokies/id538212549?mt=8"
  },
  { 
    "appId" : undefined,
    "description" : undefined,
    "developer" : "Playrix Games",
    "developerId" : 1162116447,
    "developerUrl" : "https://itunes.apple.com/au/developer/playrix-games/id1162116447?mt=8",
    "genreIds" : [ 
        "6014",
        "7012",
        "6016",
        "7015"
      ],
    "genres" : [ 
        "Games",
        "Puzzle",
        "Entertainment",
        "Simulation"
      ],
    "icon" : "http://is1.mzstatic.com/image/thumb/Purple62/v4/5f/7e/0d/5f7e0d64-3e0b-0ab2-2850-e88195aaaa83/AppIcon-1x_U007emarketing-85-220-5.png/200x200bb.png",
    "id" : "664575829",
    "released" : "2015-05-07",
    "title" : "Fishdom",
    "url" : "https://itunes.apple.com/au/app/fishdom/id664575829?mt=8"
  },
  { 
    "appId" : undefined,
    "description" : undefined,
    "developer" : "Invoice2go.com",
    "developerId" : 322773085,
    "developerUrl" : "https://itunes.apple.com/au/developer/invoice2go-com/id322773085?mt=8",
    "genreIds" : [ 
        "6000",
        "6007"
      ],
    "genres" : [ 
        "Business",
        "Productivity"
      ],
    "icon" : "http://is5.mzstatic.com/image/thumb/Purple118/v4/4e/5e/52/4e5e52f3-9bf1-6fc2-344f-c65c7ce9ae50/AppIcon-1x_U007emarketing-0-0-GLES2_U002c0-512MB-sRGB-0-0-0-85-220-0-0-0-6.png/200x200bb.png",
    "id" : "540236748",
    "released" : "2012-08-07",
    "title" : "Invoice 2go - Invoice & Quotes",
    "url" : "https://itunes.apple.com/au/app/invoice-2go-invoice-quotes/id540236748?mt=8"
  },
  { 
    "appId" : undefined,
    "description" : undefined,
    "developer" : "Urbanite Inc.",
    "developerId" : 866617780,
    "developerUrl" : "https://itunes.apple.com/au/developer/urbanite-inc/id866617780?mt=8",
    "genreIds" : [ 
        "6013",
        "6023"
      ],
    "genres" : [ 
        "Health & Fitness",
        "Food & Drink"
      ],
    "icon" : "http://is2.mzstatic.com/image/thumb/Purple62/v4/a5/f4/7f/a5f47fd4-65cc-99b6-61f7-3fcc8313cf09/AppIcon-1x_U007emarketing-85-220-0-6.png/200x200bb.png",
    "id" : "866617777",
    "released" : "2014-05-06",
    "title" : "8fit Workouts & Meal Planner",
    "url" : "https://itunes.apple.com/au/app/8fit-workouts-meal-planner/id866617777?mt=8"
  },
  { 
    "appId" : undefined,
    "description" : undefined,
    "developer" : "Universal Pictures Subscription Television Limited",
    "developerId" : 1052817339,
    "developerUrl" : "https://itunes.apple.com/au/developer/universal-pictures-subscription-television-limited/id1052817339?mt=8",
    "genreIds" : [ "6016" ],
    "genres" : [ "Entertainment" ],
    "icon" : "http://is2.mzstatic.com/image/thumb/Purple118/v4/63/45/98/6345986d-752d-103b-2712-8047120bd0c3/AppIcon-1x_U007emarketing-0-0-GLES2_U002c0-512MB-sRGB-0-0-0-85-220-0-0-0-6.png/200x200bb.png",
    "id" : "1052817340",
    "released" : "2016-03-21",
    "title" : "hayu",
    "url" : "https://itunes.apple.com/au/app/hayu/id1052817340?mt=8"
  },
  { 
    "appId" : undefined,
    "description" : undefined,
    "developer" : "eHarmony.com",
    "developerId" : 387084488,
    "developerUrl" : "https://itunes.apple.com/au/developer/eharmony-com/id387084488?mt=8",
    "genreIds" : [ 
        "6005",
        "6012"
      ],
    "genres" : [ 
        "Social Networking",
        "Lifestyle"
      ],
    "icon" : "http://is1.mzstatic.com/image/thumb/Purple128/v4/58/e9/98/58e998c7-f682-677a-8d6d-4b0652e78721/AppIcon-1x_U007emarketing-0-0-GLES2_U002c0-512MB-sRGB-0-0-0-85-220-0-0-0-4.png/200x200bb.png",
    "id" : "458272450",
    "released" : "2011-09-08",
    "title" : "eharmony Official Dating App",
    "url" : "https://itunes.apple.com/au/app/eharmony-official-dating-app/id458272450?mt=8"
  },
  { 
    "appId" : undefined,
    "description" : undefined,
    "developer" : "Murka Entertainment Limited",
    "developerId" : 476936085,
    "developerUrl" : "https://itunes.apple.com/au/developer/murka-entertainment-limited/id476936085?mt=8",
    "genreIds" : [ 
        "6014",
        "6016",
        "7006",
        "7005"
      ],
    "genres" : [ 
        "Games",
        "Entertainment",
        "Casino",
        "Card"
      ],
    "icon" : "http://is5.mzstatic.com/image/thumb/Purple118/v4/7f/f7/7f/7ff77f2c-72c6-d158-e563-aaae98770db8/AppIcon-1x_U007emarketing-0-85-220-0-5.png/200x200bb.png",
    "id" : "944158857",
    "released" : "2015-01-02",
    "title" : "Scatter Slots: Hot Vegas Slots",
    "url" : "https://itunes.apple.com/au/app/scatter-slots-hot-vegas-slots/id944158857?mt=8"
  },
  { 
    "appId" : undefined,
    "description" : undefined,
    "developer" : "Crowdstar Inc",
    "developerId" : 321598392,
    "developerUrl" : "https://itunes.apple.com/au/developer/crowdstar-inc/id321598392?mt=8",
    "genreIds" : [ 
        "6014",
        "7015",
        "7014",
        "6024"
      ],
    "genres" : [ 
        "Games",
        "Simulation",
        "Role-Playing",
        "Shopping"
      ],
    "icon" : "http://is3.mzstatic.com/image/thumb/Purple118/v4/f7/88/be/f788be55-0ea5-810d-49a4-3e287d63c9c0/AppIcon-1x_U007emarketing-85-220-5.png/200x200bb.png",
    "id" : "620112416",
    "released" : "2013-06-25",
    "title" : "Covet Fashion",
    "url" : "https://itunes.apple.com/au/app/covet-fashion/id620112416?mt=8"
  },
  { 
    "appId" : undefined,
    "description" : undefined,
    "developer" : "Fun Games For Free",
    "developerId" : 618574061,
    "developerUrl" : "https://itunes.apple.com/au/developer/fun-games-for-free/id618574061?mt=8",
    "genreIds" : [ 
        "6014",
        "7001",
        "7003",
        "6016"
      ],
    "genres" : [ 
        "Games",
        "Action",
        "Arcade",
        "Entertainment"
      ],
    "icon" : "http://is5.mzstatic.com/image/thumb/Purple128/v4/5f/8f/cb/5f8fcb5a-fd58-5d41-6c9c-93d8f99d83a0/AppIcon-1x_U007emarketing-85-220-8.png/200x200bb.png",
    "id" : "930574573",
    "released" : "2014-11-11",
    "title" : "Sniper 3D: Shoot & Survive FPS",
    "url" : "https://itunes.apple.com/au/app/sniper-3d-shoot-survive-fps/id930574573?mt=8"
  },
  { 
    "appId" : undefined,
    "description" : undefined,
    "developer" : "Genesis Technology Partners",
    "developerId" : 979011728,
    "developerUrl" : "https://itunes.apple.com/au/developer/genesis-technology-partners/id979011728?mt=8",
    "genreIds" : [ 
        "6013",
        "6012"
      ],
    "genres" : [ 
        "Health & Fitness",
        "Lifestyle"
      ],
    "icon" : "http://is3.mzstatic.com/image/thumb/Purple128/v4/99/a2/79/99a279bc-99e6-3d2f-7916-72e990db3eee/AppIcon-1x_U007emarketing-0-0-GLES2_U002c0-512MB-sRGB-0-0-0-85-220-0-0-0-5.png/200x200bb.png",
    "id" : "1264546236",
    "released" : "2017-08-22",
    "title" : "BetterMe: Weight Loss Workouts",
    "url" : "https://itunes.apple.com/au/app/betterme-weight-loss-workouts/id1264546236?mt=8"
  },
  { 
    "appId" : undefined,
    "description" : undefined,
    "developer" : "Netmarble Games Corp.",
    "developerId" : 930364579,
    "developerUrl" : "https://itunes.apple.com/au/developer/netmarble-games-corp/id930364579?mt=8",
    "genreIds" : [ 
        "6014",
        "7014"
      ],
    "genres" : [ 
        "Games",
        "Role-Playing"
      ],
    "icon" : "http://is2.mzstatic.com/image/thumb/Purple128/v4/80/e9/a5/80e9a5b6-88c2-5b6e-b453-71d513308845/AppIcon-1x_U007emarketing-85-220-0-6.png/200x200bb.png",
    "id" : "1259014919",
    "released" : "2017-11-15",
    "title" : "Lineage 2: Revolution",
    "url" : "https://itunes.apple.com/au/app/lineage-2-revolution/id1259014919?mt=8"
  },
  { 
    "appId" : undefined,
    "description" : undefined,
    "developer" : "武汉斗鱼网络科技有限公司",
    "developerId" : 863882798,
    "developerUrl" : "https://itunes.apple.com/au/developer/%E6%AD%A6%E6%B1%89%E6%96%97%E9%B1%BC%E7%BD%91%E7%BB%9C%E7%A7%91%E6%8A%80%E6%9C%89%E9%99%90%E5%85%AC%E5%8F%B8/id863882798?mt=8",
    "genreIds" : [ 
        "6016",
        "6012"
      ],
    "genres" : [ 
        "Entertainment",
        "Lifestyle"
      ],
    "icon" : "http://is3.mzstatic.com/image/thumb/Purple128/v4/16/9c/32/169c32e6-835f-0b91-a0c3-89166c97e6f5/AppIcon-1x_U007emarketing-85-220-8.png/200x200bb.png",
    "id" : "863882795",
    "released" : "2014-06-29",
    "title" : "斗鱼直播-高清游戏互动视频直播",
    "url" : "https://itunes.apple.com/au/app/%E6%96%97%E9%B1%BC%E7%9B%B4%E6%92%AD-%E9%AB%98%E6%B8%85%E6%B8%B8%E6%88%8F%E4%BA%92%E5%8A%A8%E8%A7%86%E9%A2%91%E7%9B%B4%E6%92%AD/id863882795?mt=8"
  },
  { 
    "appId" : undefined,
    "description" : undefined,
    "developer" : "Big Fish Games, Inc",
    "developerId" : 292594310,
    "developerUrl" : "https://itunes.apple.com/au/developer/big-fish-games-inc/id292594310?mt=8",
    "genreIds" : [ 
        "6014",
        "7005",
        "7006",
        "6016"
      ],
    "genres" : [ 
        "Games",
        "Card",
        "Casino",
        "Entertainment"
      ],
    "icon" : "http://is5.mzstatic.com/image/thumb/Purple118/v4/b0/a0/39/b0a0395f-9f93-2eaf-a9c6-524960d5367b/pr_source.png/200x200bb.png",
    "id" : "1090242126",
    "released" : "2016-07-12",
    "title" : "Jackpot Magic Slots™ & Casino",
    "url" : "https://itunes.apple.com/au/app/jackpot-magic-slots-casino/id1090242126?mt=8"
  },
  { 
    "appId" : undefined,
    "description" : undefined,
    "developer" : "FunPlus",
    "developerId" : 495598783,
    "developerUrl" : "https://itunes.apple.com/au/developer/funplus/id495598783?mt=8",
    "genreIds" : [ 
        "6014",
        "7014",
        "7017",
        "6005"
      ],
    "genres" : [ 
        "Games",
        "Role-Playing",
        "Strategy",
        "Social Networking"
      ],
    "icon" : "http://is1.mzstatic.com/image/thumb/Purple118/v4/82/cb/68/82cb6827-6199-4950-1335-3caafd198f3e/mzl.pdnjnewt.jpg/200x200bb.png",
    "id" : "1084930849",
    "released" : "2016-07-13",
    "title" : "King of Avalon: Dragon Warfare",
    "url" : "https://itunes.apple.com/au/app/king-of-avalon-dragon-warfare/id1084930849?mt=8"
  },
  { 
    "appId" : undefined,
    "description" : undefined,
    "developer" : "Playtika LTD",
    "developerId" : 447553567,
    "developerUrl" : "https://itunes.apple.com/au/developer/playtika-ltd/id447553567?mt=8",
    "genreIds" : [ 
        "6014",
        "7006",
        "6016",
        "7005"
      ],
    "genres" : [ 
        "Games",
        "Casino",
        "Entertainment",
        "Card"
      ],
    "icon" : "http://is3.mzstatic.com/image/thumb/Purple118/v4/a3/e4/5c/a3e45ca8-7bb0-ba03-4081-fd7bee2f860b/AppIconIPhone-1x_U007emarketing-85-220-1.png/200x200bb.png",
    "id" : "603097018",
    "released" : "2013-06-13",
    "title" : "Caesars Casino Official Slots",
    "url" : "https://itunes.apple.com/au/app/caesars-casino-official-slots/id603097018?mt=8"
  },
  { 
    "appId" : undefined,
    "description" : undefined,
    "developer" : "Product Madness",
    "developerId" : 525894639,
    "developerUrl" : "https://itunes.apple.com/au/developer/product-madness/id525894639?mt=8",
    "genreIds" : [ 
        "6014",
        "7005",
        "7006",
        "6016"
      ],
    "genres" : [ 
        "Games",
        "Card",
        "Casino",
        "Entertainment"
      ],
    "icon" : "http://is5.mzstatic.com/image/thumb/Purple118/v4/ca/81/d3/ca81d30d-a5cc-d5a9-32d4-441890bdd390/AppIcon-1x_U007emarketing-0-85-220-0-5.png/200x200bb.png",
    "id" : "1311478292",
    "released" : "2017-12-18",
    "title" : "FaFaFa™ Gold – Slots Casino",
    "url" : "https://itunes.apple.com/au/app/fafafa-gold-slots-casino/id1311478292?mt=8"
  },
  { 
    "appId" : undefined,
    "description" : undefined,
    "developer" : "Scopely",
    "developerId" : 305003647,
    "developerUrl" : "https://itunes.apple.com/au/developer/scopely/id305003647?mt=8",
    "genreIds" : [ 
        "6014",
        "7014",
        "7017",
        "6016"
      ],
    "genres" : [ 
        "Games",
        "Role-Playing",
        "Strategy",
        "Entertainment"
      ],
    "icon" : "http://is3.mzstatic.com/image/thumb/Purple118/v4/81/9e/60/819e6032-cbd3-306a-8f7c-ad75b3b6d035/AppIcon-1x_U007emarketing-85-220-5.png/200x200bb.png",
    "id" : "969316884",
    "released" : "2015-04-23",
    "title" : "Walking Dead: Road to Survival",
    "url" : "https://itunes.apple.com/au/app/walking-dead-road-to-survival/id969316884?mt=8"
  },
  { 
    "appId" : undefined,
    "description" : undefined,
    "developer" : "Supercell",
    "developerId" : 488106216,
    "developerUrl" : "https://itunes.apple.com/au/developer/supercell/id488106216?mt=8",
    "genreIds" : [ 
        "6014",
        "7015",
        "7009",
        "6016"
      ],
    "genres" : [ 
        "Games",
        "Simulation",
        "Family",
        "Entertainment"
      ],
    "icon" : "http://is1.mzstatic.com/image/thumb/Purple128/v4/69/8a/47/698a47dc-08ec-d2e3-ebf3-39a5d33d117d/AppIcon-1x_U007emarketing-0-85-220-0-6.png/200x200bb.png",
    "id" : "506627515",
    "released" : "2012-06-21",
    "title" : "Hay Day",
    "url" : "https://itunes.apple.com/au/app/hay-day/id506627515?mt=8"
  },
  { 
    "appId" : undefined,
    "description" : undefined,
    "developer" : "N3TWORK Inc.",
    "developerId" : 766104536,
    "developerUrl" : "https://itunes.apple.com/au/developer/n3twork-inc/id766104536?mt=8",
    "genreIds" : [ 
        "6014",
        "7012",
        "7014"
      ],
    "genres" : [ 
        "Games",
        "Puzzle",
        "Role-Playing"
      ],
    "icon" : "http://is3.mzstatic.com/image/thumb/Purple128/v4/eb/6b/bf/eb6bbf0b-afe5-e6db-4158-3968eb21fc22/mzl.bvjhcltc.png/200x200bb.png",
    "id" : "1032040117",
    "released" : "2015-11-13",
    "title" : "Legendary - Game of Heroes",
    "url" : "https://itunes.apple.com/au/app/legendary-game-of-heroes/id1032040117?mt=8"
  },
  { 
    "appId" : undefined,
    "description" : undefined,
    "developer" : "Gram Games",
    "developerId" : 1202264615,
    "developerUrl" : "https://itunes.apple.com/au/developer/gram-games/id1202264615?mt=8",
    "genreIds" : [ 
        "6014",
        "7012",
        "7009"
      ],
    "genres" : [ 
        "Games",
        "Puzzle",
        "Family"
      ],
    "icon" : "http://is1.mzstatic.com/image/thumb/Purple128/v4/fd/79/09/fd790935-77df-a53d-b975-e833ebbb4ad2/AppIcon-1x_U007emarketing-85-220-7.png/200x200bb.png",
    "id" : "1208952944",
    "released" : "2017-03-07",
    "title" : "Merge Dragons!",
    "url" : "https://itunes.apple.com/au/app/merge-dragons/id1208952944?mt=8"
  },
  { 
    "appId" : undefined,
    "description" : undefined,
    "developer" : "NBA",
    "developerId" : 398083945,
    "developerUrl" : "https://itunes.apple.com/au/developer/nba/id398083945?mt=8",
    "genreIds" : [ 
        "6004",
        "6016"
      ],
    "genres" : [ 
        "Sports",
        "Entertainment"
      ],
    "icon" : "http://is4.mzstatic.com/image/thumb/Purple128/v4/a9/f4/5e/a9f45e66-b50f-6779-7f6c-66754a3dd460/AppIcon-1x_U007emarketing-85-220-0-6.png/200x200bb.png",
    "id" : "484672289",
    "released" : "2011-12-21",
    "title" : "2017-18 NBA App",
    "url" : "https://itunes.apple.com/au/app/2017-18-nba-app/id484672289?mt=8"
  },
  { 
    "appId" : undefined,
    "description" : undefined,
    "developer" : "Gismart",
    "developerId" : 666830030,
    "developerUrl" : "https://itunes.apple.com/au/developer/gismart/id666830030?mt=8",
    "genreIds" : [ 
        "6011",
        "6016"
      ],
    "genres" : [ 
        "Music",
        "Entertainment"
      ],
    "icon" : "http://is2.mzstatic.com/image/thumb/Purple128/v4/e9/5a/94/e95a9477-32a8-ab60-675e-a98c5f965aa4/AppIcon-1x_U007emarketing-85-220-0-6.png/200x200bb.png",
    "id" : "1141835258",
    "released" : "2016-12-01",
    "title" : "Beat Maker Go - Sound Effects",
    "url" : "https://itunes.apple.com/au/app/beat-maker-go-sound-effects/id1141835258?mt=8"
  },
  { 
    "appId" : undefined,
    "description" : undefined,
    "developer" : "HAPPN SAS",
    "developerId" : 489185851,
    "developerUrl" : "https://itunes.apple.com/au/developer/happn-sas/id489185851?mt=8",
    "genreIds" : [ 
        "6012",
        "6005"
      ],
    "genres" : [ 
        "Lifestyle",
        "Social Networking"
      ],
    "icon" : "http://is5.mzstatic.com/image/thumb/Purple118/v4/21/13/df/2113df95-05aa-dd0d-c432-e1cb4539d02b/AppIcon-1x_U007emarketing-85-220-5.png/200x200bb.png",
    "id" : "489185828",
    "released" : "2012-03-07",
    "title" : "happn — Dating app",
    "url" : "https://itunes.apple.com/au/app/happn-dating-app/id489185828?mt=8"
  },
  { 
    "appId" : undefined,
    "description" : undefined,
    "developer" : "Playdemic",
    "developerId" : 505151958,
    "developerUrl" : "https://itunes.apple.com/au/developer/playdemic/id505151958?mt=8",
    "genreIds" : [ 
        "6014",
        "6004",
        "7015",
        "7016"
      ],
    "genres" : [ 
        "Games",
        "Sports",
        "Simulation",
        "Sports"
      ],
    "icon" : "http://is3.mzstatic.com/image/thumb/Purple128/v4/08/5a/d1/085ad1f8-936a-2eb7-7be7-d1c623028ed7/AppIcon-1x_U007emarketing-85-220-0-6.png/200x200bb.png",
    "id" : "1089225191",
    "released" : "2016-12-12",
    "title" : "Golf Clash",
    "url" : "https://itunes.apple.com/au/app/golf-clash/id1089225191?mt=8"
  },
  { 
    "appId" : undefined,
    "description" : undefined,
    "developer" : "Electronic Arts",
    "developerId" : 284800461,
    "developerUrl" : "https://itunes.apple.com/au/developer/electronic-arts/id284800461?mt=8",
    "genreIds" : [ 
        "6014",
        "6016",
        "7015",
        "7002"
      ],
    "genres" : [ 
        "Games",
        "Entertainment",
        "Simulation",
        "Adventure"
      ],
    "icon" : "http://is5.mzstatic.com/image/thumb/Purple62/v4/0e/70/23/0e7023a9-8759-486c-5502-ea3dabe82cf9/AppIcon-1x_U007emarketing-0-85-220-0-6.png/200x200bb.png",
    "id" : "498375892",
    "released" : "2012-02-29",
    "title" : "The Simpsons™: Tapped Out",
    "url" : "https://itunes.apple.com/au/app/the-simpsons-tapped-out/id498375892?mt=8"
  },
  { 
    "appId" : undefined,
    "description" : undefined,
    "developer" : "Kimberly Smith",
    "developerId" : 1341283532,
    "developerUrl" : "https://itunes.apple.com/au/developer/kimberly-smith/id1341283532?mt=8",
    "genreIds" : [ 
        "6014",
        "7019",
        "7012"
      ],
    "genres" : [ 
        "Games",
        "Word",
        "Puzzle"
      ],
    "icon" : "http://is4.mzstatic.com/image/thumb/Purple128/v4/44/7d/f4/447df438-b621-3175-5721-3eb407dd46b7/AppIcon-1x_U007emarketing-85-220-0-6.png/200x200bb.png",
    "id" : "1341283533",
    "released" : "2018-02-10",
    "title" : "Quiz Crossword",
    "url" : "https://itunes.apple.com/au/app/quiz-crossword/id1341283533?mt=8"
  },
  { 
    "appId" : undefined,
    "description" : undefined,
    "developer" : "TOP GAMES INC.",
    "developerId" : 1050386041,
    "developerUrl" : "https://itunes.apple.com/au/developer/top-games-inc/id1050386041?mt=8",
    "genreIds" : [ "6014" ],
    "genres" : [ "Games" ],
    "icon" : "http://is3.mzstatic.com/image/thumb/Purple118/v4/55/41/de/5541decf-44a2-12c6-063d-3c2bab00cafc/AppIcon-1x_U007emarketing-0-85-220-0-5.png/200x200bb.png",
    "id" : "1098157959",
    "released" : "2016-04-27",
    "title" : "Evony",
    "url" : "https://itunes.apple.com/au/app/evony/id1098157959?mt=8"
  },
  { 
    "appId" : undefined,
    "description" : undefined,
    "developer" : "Visual Supply Company",
    "developerId" : 513526768,
    "developerUrl" : "https://itunes.apple.com/au/developer/visual-supply-company/id513526768?mt=8",
    "genreIds" : [ 
        "6008",
        "6012"
      ],
    "genres" : [ 
        "Photo & Video",
        "Lifestyle"
      ],
    "icon" : "http://is4.mzstatic.com/image/thumb/Purple118/v4/50/f4/88/50f4886b-184f-4194-c0e8-496669afa75c/AppIcon-1x_U007emarketing-85-220-0-5.png/200x200bb.png",
    "id" : "588013838",
    "released" : "2013-06-06",
    "title" : "VSCO",
    "url" : "https://itunes.apple.com/au/app/vsco/id588013838?mt=8"
  },
  { 
    "appId" : undefined,
    "description" : undefined,
    "developer" : "Roblox Corporation",
    "developerId" : 431946155,
    "developerUrl" : "https://itunes.apple.com/au/developer/roblox-corporation/id431946155?mt=8",
    "genreIds" : [ 
        "6014",
        "7002",
        "6016",
        "7001"
      ],
    "genres" : [ 
        "Games",
        "Adventure",
        "Entertainment",
        "Action"
      ],
    "icon" : "http://is2.mzstatic.com/image/thumb/Purple128/v4/3d/2b/19/3d2b1983-321d-ee90-58c8-11f42f19f333/AppIcon-1x_U007emarketing-85-220-6.png/200x200bb.png",
    "id" : "431946152",
    "released" : "2011-05-26",
    "title" : "ROBLOX",
    "url" : "https://itunes.apple.com/au/app/roblox/id431946152?mt=8"
  },
  { 
    "appId" : undefined,
    "description" : undefined,
    "developer" : "Rovio Entertainment Oyj",
    "developerId" : 298910979,
    "developerUrl" : "https://itunes.apple.com/au/developer/rovio-entertainment-oyj/id298910979?mt=8",
    "genreIds" : [ 
        "6014",
        "7012",
        "7001"
      ],
    "genres" : [ 
        "Games",
        "Puzzle",
        "Action"
      ],
    "icon" : "http://is3.mzstatic.com/image/thumb/Purple118/v4/f7/81/d4/f781d473-b559-2a3d-6e14-fbba30a5c325/AppIcon-1x_U007emarketing-85-220-0-8.png/200x200bb.png",
    "id" : "880047117",
    "released" : "2015-04-22",
    "title" : "Angry Birds 2",
    "url" : "https://itunes.apple.com/au/app/angry-birds-2/id880047117?mt=8"
  },
  { 
    "appId" : undefined,
    "description" : undefined,
    "developer" : "NaturalMotion",
    "developerId" : 330281898,
    "developerUrl" : "https://itunes.apple.com/au/developer/naturalmotion/id330281898?mt=8",
    "genreIds" : [ 
        "6014",
        "6016",
        "7013",
        "7003"
      ],
    "genres" : [ 
        "Games",
        "Entertainment",
        "Racing",
        "Arcade"
      ],
    "icon" : "http://is2.mzstatic.com/image/thumb/Purple118/v4/30/18/a1/3018a1a7-d2a4-17a1-b13e-e0605b8e3b27/AppIcon-1x_U007emarketing-85-220-9.png/200x200bb.png",
    "id" : "887947640",
    "released" : "2016-01-13",
    "title" : "CSR Racing 2",
    "url" : "https://itunes.apple.com/au/app/csr-racing-2/id887947640?mt=8"
  },
  { 
    "appId" : undefined,
    "description" : undefined,
    "developer" : "NetEase Games",
    "developerId" : 874255382,
    "developerUrl" : "https://itunes.apple.com/au/developer/netease-games/id874255382?mt=8",
    "genreIds" : [ 
        "6014",
        "7001",
        "7002"
      ],
    "genres" : [ 
        "Games",
        "Action",
        "Adventure"
      ],
    "icon" : "http://is3.mzstatic.com/image/thumb/Purple128/v4/c0/0a/48/c00a4825-7a43-ba26-b7aa-a23851630d27/AppIcon-1x_U007emarketing-85-220-0-6.png/200x200bb.png",
    "id" : "1307961750",
    "released" : "2017-11-14",
    "title" : "Rules of Survival",
    "url" : "https://itunes.apple.com/au/app/rules-of-survival/id1307961750?mt=8"
  },
  { 
    "appId" : undefined,
    "description" : undefined,
    "developer" : "Viber Media SARL.",
    "developerId" : 382617923,
    "developerUrl" : "https://itunes.apple.com/au/developer/viber-media-sarl/id382617923?mt=8",
    "genreIds" : [ 
        "6005",
        "6002"
      ],
    "genres" : [ 
        "Social Networking",
        "Utilities"
      ],
    "icon" : "http://is4.mzstatic.com/image/thumb/Purple118/v4/c8/cd/62/c8cd62eb-c8f4-399c-2936-415c16dc3340/AppIcon-1x_U007emarketing-0-85-220-0-6.png/200x200bb.png",
    "id" : "382617920",
    "released" : "2010-12-02",
    "title" : "Viber Messenger – Text & Call",
    "url" : "https://itunes.apple.com/au/app/viber-messenger-text-call/id382617920?mt=8"
  },
  { 
    "appId" : undefined,
    "description" : undefined,
    "developer" : "King",
    "developerId" : 526656015,
    "developerUrl" : "https://itunes.apple.com/au/developer/king/id526656015?mt=8",
    "genreIds" : [ 
        "6014",
        "6016",
        "7012",
        "7003"
      ],
    "genres" : [ 
        "Games",
        "Entertainment",
        "Puzzle",
        "Arcade"
      ],
    "icon" : "http://is3.mzstatic.com/image/thumb/Purple128/v4/5b/fa/6b/5bfa6b21-ca26-04d9-3bd9-f46fd7574caa/mzl.lpuofavy.jpg/200x200bb.png",
    "id" : "608206510",
    "released" : "2014-01-02",
    "title" : "Farm Heroes Saga",
    "url" : "https://itunes.apple.com/au/app/farm-heroes-saga/id608206510?mt=8"
  },
  { 
    "appId" : undefined,
    "description" : undefined,
    "developer" : "Moon Active",
    "developerId" : 470556954,
    "developerUrl" : "https://itunes.apple.com/au/developer/moon-active/id470556954?mt=8",
    "genreIds" : [ 
        "6014",
        "7003",
        "7002"
      ],
    "genres" : [ 
        "Games",
        "Arcade",
        "Adventure"
      ],
    "icon" : "http://is5.mzstatic.com/image/thumb/Purple128/v4/5d/ab/8e/5dab8e4e-95d8-bfff-a65b-ce66ee0973f7/AppIcon-1x_U007emarketing-0-85-220-0-5.png/200x200bb.png",
    "id" : "406889139",
    "released" : "2010-12-11",
    "title" : "Coin Master",
    "url" : "https://itunes.apple.com/au/app/coin-master/id406889139?mt=8"
  },
  { 
    "appId" : undefined,
    "description" : undefined,
    "developer" : "RSVP.com.au",
    "developerId" : 922792170,
    "developerUrl" : "https://itunes.apple.com/au/developer/rsvp-com-au/id922792170?mt=8",
    "genreIds" : [ 
        "6005",
        "6012"
      ],
    "genres" : [ 
        "Social Networking",
        "Lifestyle"
      ],
    "icon" : "http://is3.mzstatic.com/image/thumb/Purple128/v4/a2/7a/e8/a27ae8ad-fa4c-5474-9d02-51d252daaeab/AppIcon-1x_U007emarketing-85-220-9.png/200x200bb.png",
    "id" : "397280080",
    "released" : "2010-11-22",
    "title" : "RSVP - Australia’s Dating Site",
    "url" : "https://itunes.apple.com/au/app/rsvp-australias-dating-site/id397280080?mt=8"
  },
  { 
    "appId" : undefined,
    "description" : undefined,
    "developer" : "Badoo Software Ltd",
    "developerId" : 351331197,
    "developerUrl" : "https://itunes.apple.com/au/developer/badoo-software-ltd/id351331197?mt=8",
    "genreIds" : [ 
        "6005",
        "6012"
      ],
    "genres" : [ 
        "Social Networking",
        "Lifestyle"
      ],
    "icon" : "http://is2.mzstatic.com/image/thumb/Purple118/v4/45/eb/82/45eb82ab-f13f-f4ff-5728-977e51f7de8a/AppIcon-1x_U007emarketing-0-0-GLES2_U002c0-512MB-sRGB-0-0-0-85-220-0-0-0-8.png/200x200bb.png",
    "id" : "351331194",
    "released" : "2010-12-20",
    "title" : "Badoo - The Dating App",
    "url" : "https://itunes.apple.com/au/app/badoo-the-dating-app/id351331194?mt=8"
  },
  { 
    "appId" : undefined,
    "description" : undefined,
    "developer" : "BitRhymes Inc.",
    "developerId" : 311349149,
    "developerUrl" : "https://itunes.apple.com/au/developer/bitrhymes-inc/id311349149?mt=8",
    "genreIds" : [ 
        "6014",
        "6016",
        "7005",
        "7006"
      ],
    "genres" : [ 
        "Games",
        "Entertainment",
        "Card",
        "Casino"
      ],
    "icon" : "http://is1.mzstatic.com/image/thumb/Purple128/v4/7a/50/52/7a5052b4-30e8-3470-db12-10d1f27c13d5/mzl.eaozfrha.jpg/200x200bb.png",
    "id" : "509098112",
    "released" : "2012-05-01",
    "title" : "Bingo Bash: Bingo & Slots",
    "url" : "https://itunes.apple.com/au/app/bingo-bash-bingo-slots/id509098112?mt=8"
  },
  { 
    "appId" : undefined,
    "description" : undefined,
    "developer" : "MeetMe, Inc.",
    "developerId" : 372648915,
    "developerUrl" : "https://itunes.apple.com/au/developer/meetme-inc/id372648915?mt=8",
    "genreIds" : [ 
        "6005",
        "6016"
      ],
    "genres" : [ 
        "Social Networking",
        "Entertainment"
      ],
    "icon" : "http://is2.mzstatic.com/image/thumb/Purple128/v4/bb/1e/5f/bb1e5f87-46d9-5b3e-ebd4-394c76aeda77/AppIcon-1x_U007emarketing-85-220-0-4.png/200x200bb.png",
    "id" : "372648912",
    "released" : "2010-05-28",
    "title" : "MeetMe - Meet new people!",
    "url" : "https://itunes.apple.com/au/app/meetme-meet-new-people/id372648912?mt=8"
  },
  { 
    "appId" : undefined,
    "description" : undefined,
    "developer" : "Playrix Games",
    "developerId" : 1162116447,
    "developerUrl" : "https://itunes.apple.com/au/developer/playrix-games/id1162116447?mt=8",
    "genreIds" : [ 
        "6014",
        "6016",
        "7002",
        "7015"
      ],
    "genres" : [ 
        "Games",
        "Entertainment",
        "Adventure",
        "Simulation"
      ],
    "icon" : "http://is1.mzstatic.com/image/thumb/Purple62/v4/79/2f/df/792fdf15-7fb8-5f54-92a4-a8fa05022818/AppIcon-1x_U007emarketing-85-220-9.png/200x200bb.png",
    "id" : "638689075",
    "released" : "2013-09-30",
    "title" : "Township",
    "url" : "https://itunes.apple.com/au/app/township/id638689075?mt=8"
  },
  { 
    "appId" : undefined,
    "description" : undefined,
    "developer" : "Zodiac Consulting Limited",
    "developerId" : 1004615215,
    "developerUrl" : "https://itunes.apple.com/au/developer/zodiac-consulting-limited/id1004615215?mt=8",
    "genreIds" : [ "6012" ],
    "genres" : [ "Lifestyle" ],
    "icon" : "http://is3.mzstatic.com/image/thumb/Purple128/v4/68/fb/42/68fb42bb-7b80-589a-0462-4dd97dfeeb9f/AppIcon-1x_U007emarketing-85-220-0-9.png/200x200bb.png",
    "id" : "1004615216",
    "released" : "2015-11-09",
    "title" : "Zodiac Touch - psychic reading",
    "url" : "https://itunes.apple.com/au/app/zodiac-touch-psychic-reading/id1004615216?mt=8"
  },
  { 
    "appId" : undefined,
    "description" : undefined,
    "developer" : "Blizzard Entertainment, Inc.",
    "developerId" : 306862900,
    "developerUrl" : "https://itunes.apple.com/au/developer/blizzard-entertainment-inc/id306862900?mt=8",
    "genreIds" : [ 
        "6014",
        "6016",
        "7005",
        "7017"
      ],
    "genres" : [ 
        "Games",
        "Entertainment",
        "Card",
        "Strategy"
      ],
    "icon" : "http://is3.mzstatic.com/image/thumb/Purple118/v4/1c/01/f0/1c01f068-ca26-b3e5-9c8a-0da404822a9f/mzl.deoavxtl.png/200x200bb.png",
    "id" : "625257520",
    "released" : "2014-04-02",
    "title" : "Hearthstone",
    "url" : "https://itunes.apple.com/au/app/hearthstone/id625257520?mt=8"
  }
]
