[ 
  { 
    "appId" : undefined,
    "description" : undefined,
    "developer" : "HyperBeard Games",
    "developerId" : 1169188578,
    "developerUrl" : "https://itunes.apple.com/ph/developer/hyperbeard-games/id1169188578?mt=8",
    "genreIds" : [ 
        "6014",
        "7009",
        "6016",
        "7002"
      ],
    "genres" : [ 
        "Games",
        "Family",
        "Entertainment",
        "Adventure"
      ],
    "icon" : "http://is4.mzstatic.com/image/thumb/Purple118/v4/c3/39/fe/c339fec0-87a7-928b-ab34-35b22aefd819/AppIcon-1x_U007emarketing-0-85-220-0-7.png/200x200bb.png",
    "id" : "1329062940",
    "released" : "2018-03-12",
    "title" : "KleptoCats 2",
    "url" : "https://itunes.apple.com/ph/app/kleptocats-2/id1329062940?mt=8"
  },
  { 
    "appId" : undefined,
    "description" : undefined,
    "developer" : "BANDAI NAMCO Entertainment Europe",
    "developerId" : 580781332,
    "developerUrl" : "https://itunes.apple.com/ph/developer/bandai-namco-entertainment-europe/id580781332?mt=8",
    "genreIds" : [ 
        "6014",
        "6016",
        "7015",
        "7014"
      ],
    "genres" : [ 
        "Games",
        "Entertainment",
        "Simulation",
        "Role-Playing"
      ],
    "icon" : "http://is4.mzstatic.com/image/thumb/Purple118/v4/86/d1/3b/86d13b88-67d2-5d61-7429-301d09de0354/AppIcon-1x_U007emarketing-0-85-220-0-8.png/200x200bb.png",
    "id" : "1267861706",
    "released" : "2018-03-14",
    "title" : "My Tamagotchi Forever",
    "url" : "https://itunes.apple.com/ph/app/my-tamagotchi-forever/id1267861706?mt=8"
  },
  { 
    "appId" : undefined,
    "description" : undefined,
    "developer" : "Kwalee",
    "developerId" : 497961736,
    "developerUrl" : "https://itunes.apple.com/ph/developer/kwalee/id497961736?mt=8",
    "genreIds" : [ 
        "6014",
        "7003",
        "7012"
      ],
    "genres" : [ 
        "Games",
        "Arcade",
        "Puzzle"
      ],
    "icon" : "http://is1.mzstatic.com/image/thumb/Purple128/v4/6b/ab/97/6bab970c-2cdd-0f99-1f1a-d6f339587713/AppIcon-1x_U007emarketing-85-220-8.png/200x200bb.png",
    "id" : "1273311118",
    "released" : "2017-10-10",
    "title" : "SPILLZ",
    "url" : "https://itunes.apple.com/ph/app/spillz/id1273311118?mt=8"
  },
  { 
    "appId" : undefined,
    "description" : undefined,
    "developer" : "MOBIRIX",
    "developerId" : 349276666,
    "developerUrl" : "https://itunes.apple.com/ph/developer/mobirix/id349276666?mt=8",
    "genreIds" : [ 
        "6014",
        "7003",
        "6016",
        "7002"
      ],
    "genres" : [ 
        "Games",
        "Arcade",
        "Entertainment",
        "Adventure"
      ],
    "icon" : "http://is2.mzstatic.com/image/thumb/Purple128/v4/ed/d1/8d/edd18d34-71ee-3d06-96b0-2f1d5cd2ae9b/AppIcon-1x_U007emarketing-85-220-5.png/200x200bb.png",
    "id" : "1335884905",
    "released" : "2018-03-13",
    "title" : "Jump Knights",
    "url" : "https://itunes.apple.com/ph/app/jump-knights/id1335884905?mt=8"
  },
  { 
    "appId" : undefined,
    "description" : undefined,
    "developer" : "League of Geeks",
    "developerId" : 1154749672,
    "developerUrl" : "https://itunes.apple.com/ph/developer/league-of-geeks/id1154749672?mt=8",
    "genreIds" : [ 
        "6014",
        "7004",
        "7017"
      ],
    "genres" : [ 
        "Games",
        "Board",
        "Strategy"
      ],
    "icon" : "http://is4.mzstatic.com/image/thumb/Purple118/v4/70/84/b0/7084b0f1-2055-f2f6-48b3-1c09f035e966/AppIcon-1x_U007emarketing-85-220-0-8.png/200x200bb.png",
    "id" : "1154749673",
    "released" : "2018-03-22",
    "title" : "Armello",
    "url" : "https://itunes.apple.com/ph/app/armello/id1154749673?mt=8"
  },
  { 
    "appId" : undefined,
    "description" : undefined,
    "developer" : "Simple Machine, LLC",
    "developerId" : 440559596,
    "developerUrl" : "https://itunes.apple.com/ph/developer/simple-machine-llc/id440559596?mt=8",
    "genreIds" : [ 
        "6014",
        "7012",
        "7003"
      ],
    "genres" : [ 
        "Games",
        "Puzzle",
        "Arcade"
      ],
    "icon" : "http://is5.mzstatic.com/image/thumb/Purple118/v4/87/0f/5e/870f5ea0-6886-f4d3-a402-212ff1634339/AppIcon-1x_U007emarketing-85-220-5.png/200x200bb.png",
    "id" : "1315674869",
    "released" : "2018-03-15",
    "title" : "_-_",
    "url" : "https://itunes.apple.com/ph/app//id1315674869?mt=8"
  },
  { 
    "appId" : undefined,
    "description" : undefined,
    "developer" : "Kyrylo Kuzyk",
    "developerId" : 1096049714,
    "developerUrl" : "https://itunes.apple.com/ph/developer/kyrylo-kuzyk/id1096049714?mt=8",
    "genreIds" : [ 
        "6014",
        "7012"
      ],
    "genres" : [ 
        "Games",
        "Puzzle"
      ],
    "icon" : "http://is1.mzstatic.com/image/thumb/Purple118/v4/4a/dc/1c/4adc1c0f-27a1-cbb2-7667-fdd18afc98ca/AppIcon-1x_U007emarketing-85-220-7.png/200x200bb.png",
    "id" : "1244456273",
    "released" : "2018-03-12",
    "title" : ".projekt",
    "url" : "https://itunes.apple.com/ph/app/projekt/id1244456273?mt=8"
  },
  { 
    "appId" : undefined,
    "description" : undefined,
    "developer" : "Kiseki Games",
    "developerId" : 1192670762,
    "developerUrl" : "https://itunes.apple.com/ph/developer/kiseki-games/id1192670762?mt=8",
    "genreIds" : [ 
        "6014",
        "6016",
        "7003",
        "7001"
      ],
    "genres" : [ 
        "Games",
        "Entertainment",
        "Arcade",
        "Action"
      ],
    "icon" : "http://is5.mzstatic.com/image/thumb/Purple62/v4/ba/bd/16/babd16a5-ef28-9cb5-bfa3-abc73a6678c3/AppIcon-1x_U007emarketing-0-P3-85-220-0-7.png/200x200bb.png",
    "id" : "1348577303",
    "released" : "2018-03-14",
    "title" : "Go Go Jelly!",
    "url" : "https://itunes.apple.com/ph/app/go-go-jelly/id1348577303?mt=8"
  },
  { 
    "appId" : undefined,
    "description" : undefined,
    "developer" : "Upopa Entertainment Ltd",
    "developerId" : 1140797199,
    "developerUrl" : "https://itunes.apple.com/ph/developer/upopa-entertainment-ltd/id1140797199?mt=8",
    "genreIds" : [ 
        "6014",
        "7014",
        "6016",
        "7001"
      ],
    "genres" : [ 
        "Games",
        "Role-Playing",
        "Entertainment",
        "Action"
      ],
    "icon" : "http://is5.mzstatic.com/image/thumb/Purple128/v4/61/08/a2/6108a23c-0c4d-bb65-7d89-221292bde0d4/AppIcon-1x_U007emarketing-85-220-8.png/200x200bb.png",
    "id" : "1289141566",
    "released" : "2018-02-08",
    "title" : "Hopeless Heroes: Tap Attack",
    "url" : "https://itunes.apple.com/ph/app/hopeless-heroes-tap-attack/id1289141566?mt=8"
  },
  { 
    "appId" : undefined,
    "description" : undefined,
    "developer" : "GameHouse",
    "developerId" : 284837569,
    "developerUrl" : "https://itunes.apple.com/ph/developer/gamehouse/id284837569?mt=8",
    "genreIds" : [ 
        "6014",
        "7002",
        "7015"
      ],
    "genres" : [ 
        "Games",
        "Adventure",
        "Simulation"
      ],
    "icon" : "http://is3.mzstatic.com/image/thumb/Purple128/v4/4b/42/cb/4b42cbd4-8bd1-7042-d623-6785c319c75e/AppIcon-1x_U007emarketing-85-220-8.png/200x200bb.png",
    "id" : "1242210377",
    "released" : "2018-02-22",
    "title" : "Parker & Lane",
    "url" : "https://itunes.apple.com/ph/app/parker-lane/id1242210377?mt=8"
  },
  { 
    "appId" : undefined,
    "description" : undefined,
    "developer" : "DIGITAL MELODY GAMES KITAJEWSKI I STALEWSKI SPOLKA JAWNA",
    "developerId" : 774942875,
    "developerUrl" : "https://itunes.apple.com/ph/developer/digital-melody-games-kitajewski-i-stalewski-spolka-jawna/id774942875?mt=8",
    "genreIds" : [ 
        "6014",
        "7002",
        "6016",
        "7003"
      ],
    "genres" : [ 
        "Games",
        "Adventure",
        "Entertainment",
        "Arcade"
      ],
    "icon" : "http://is3.mzstatic.com/image/thumb/Purple128/v4/fe/2e/53/fe2e5309-4c4f-c607-2ff9-d290092994b0/AppIcon-1x_U007emarketing-0-85-220-0-8.png/200x200bb.png",
    "id" : "1272045722",
    "released" : "2018-03-14",
    "title" : "Runventure",
    "url" : "https://itunes.apple.com/ph/app/runventure/id1272045722?mt=8"
  },
  { 
    "appId" : undefined,
    "description" : undefined,
    "developer" : "Appsolute Games LLC",
    "developerId" : 602062365,
    "developerUrl" : "https://itunes.apple.com/ph/developer/appsolute-games-llc/id602062365?mt=8",
    "genreIds" : [ 
        "6014",
        "7003",
        "7001",
        "6016"
      ],
    "genres" : [ 
        "Games",
        "Arcade",
        "Action",
        "Entertainment"
      ],
    "icon" : "http://is4.mzstatic.com/image/thumb/Purple128/v4/27/a4/ce/27a4ceba-d020-69f6-030c-4e49e7a18937/AppIcon-1x_U007emarketing-85-220-8.png/200x200bb.png",
    "id" : "1345028045",
    "released" : "2018-03-14",
    "title" : "Quick Jumps!",
    "url" : "https://itunes.apple.com/ph/app/quick-jumps/id1345028045?mt=8"
  }
]
